turbineml/__init__.py
turbineml/configuration.py
turbineml/jobs.py
turbineml/models.py
turbineml/version.py
turbineml/volume_cache.py
turbineml/volumes.py
turbineml/cli/__init__.py
turbineml/cli/main.py
turbineml/internal/__init__.py
turbineml/internal/file_wrapper.py
turbineml-0.0.3.post6.dist-info/LICENSE
turbineml-0.0.3.post6.dist-info/METADATA
turbineml-0.0.3.post6.dist-info/WHEEL
turbineml-0.0.3.post6.dist-info/entry_points.txt
turbineml-0.0.3.post6.dist-info/top_level.txt
turbineml-0.0.3.post6.dist-info/RECORD
