Metadata-Version: 2.1
Name: turbineml
Version: 0.0.3.post6
Summary: Turbine ML
Home-page: https://github.com/turbineml/turbine-client
Author: Turbine ML
Author-email: info@turbineml.com
License: UNKNOWN
Project-URL: Bug Tracker, https://github.com/turbineml/turbine-client/issues
Platform: UNKNOWN
Classifier: Programming Language :: Python :: 3
Classifier: License :: OSI Approved :: Apache Software License
Classifier: Operating System :: OS Independent
Requires-Python: >=3.6
Requires-Dist: requests (>=2.22.0)
Requires-Dist: rich (>=10.0.0)
Requires-Dist: PyYAML (>=5.4.0)
Requires-Dist: stringcase (>=1.2.0)
Requires-Dist: gql[requests] (>=3.0.0a6)
